{
  "info": {
    "_postman_id": "dd3f4e36-2410-4474-a4ee-bcb5f399422c",
    "name": "-ForServOs-",
    "description": "Collection da API ForServOs.\n\nEsta collection contém todos os endpoints do sistema de gerenciamento de ordens de serviço, incluindo autenticação, usuários, clientes, produtos e ordens de serviço.\n\n🔐 Autenticação:\n\n- Realize o login em \"Auth > Login\"\n    \n- O token JWT será salvo automaticamente na variável {{token}}\n    \n- As demais requisições utilizam este token via Bearer\n    \n\n⚙️ Variáveis:\n\n- {{base_url}} → URL base da API (ex: [http://localhost:8000](http://localhost:8000))\n    \n- {{token}} → Token JWT gerado no login\n    \n\n📌 Observações:\n\n- Rotas protegidas exigem autenticação\n    \n- Algumas rotas exigem perfil \"admin\"\n    \n- A criação de Ordem de Serviço cria automaticamente o cliente caso não exista (via CPF)\n    \n\n🧪 Fluxo recomendado para testes:\n\n1. Auth > Login\n    \n2. Criar dados base (Clientes, Produtos, etc.)\n    \n3. Criar Ordem de Serviço\n    \n4. Testar listagens, atualizações e exclusões",
    "schema": "https://schema.getpostman.com/json/collection/v2.1.0/collection.json",
    "_exporter_id": "17016924"
  },
  "item": [
    {
      "name": "Cidade",
      "item": [
        {
          "name": "CreateCidade",
          "request": {
            "auth": {
              "type": "bearer",
              "bearer": [
                {
                  "key": "token",
                  "value": "{{token}}",
                  "type": "string"
                }
              ]
            },
            "method": "POST",
            "header": [
              {
                "key": "Content-Type",
                "value": "application/json",
                "type": "text"
              }
            ],
            "body": {
              "mode": "raw",
              "raw": "{\r\n  \"nomeCidade\": \"Bauru\",\r\n  \"estadoId\":1\r\n}",
              "options": {
                "raw": {
                  "language": "json"
                }
              }
            },
            "url": {
              "raw": "{{base_url}}/cidade/create",
              "host": [
                "{{base_url}}"
              ],
              "path": [
                "cidade",
                "create"
              ]
            }
          },
          "response": []
        },
        {
          "name": "ListCidade",
          "protocolProfileBehavior": {
            "disableBodyPruning": true
          },
          "request": {
            "auth": {
              "type": "bearer",
              "bearer": [
                {
                  "key": "token",
                  "value": "{{token}}",
                  "type": "string"
                }
              ]
            },
            "method": "GET",
            "header": [
              {
                "key": "Content-Type",
                "value": "application/json",
                "type": "text"
              }
            ],
            "body": {
              "mode": "raw",
              "raw": "",
              "options": {
                "raw": {
                  "language": "json"
                }
              }
            },
            "url": {
              "raw": "{{base_url}}/cidade/list",
              "host": [
                "{{base_url}}"
              ],
              "path": [
                "cidade",
                "list"
              ]
            }
          },
          "response": []
        },
        {
          "name": "UpdateCidade",
          "request": {
            "auth": {
              "type": "bearer",
              "bearer": [
                {
                  "key": "token",
                  "value": "{{token}}",
                  "type": "string"
                }
              ]
            },
            "method": "PUT",
            "header": [
              {
                "key": "Content-Type",
                "value": "application/json",
                "type": "text"
              }
            ],
            "body": {
              "mode": "raw",
              "raw": "{\r\n  \"id\":3,\r\n  \"nomeCidade\": \"BAURUUUU\",\r\n  \"estadoId\":1\r\n}",
              "options": {
                "raw": {
                  "language": "json"
                }
              }
            },
            "url": {
              "raw": "{{base_url}}/cidade/update",
              "host": [
                "{{base_url}}"
              ],
              "path": [
                "cidade",
                "update"
              ]
            }
          },
          "response": []
        },
        {
          "name": "DeleteCidade",
          "request": {
            "auth": {
              "type": "bearer",
              "bearer": [
                {
                  "key": "token",
                  "value": "{{token}}",
                  "type": "string"
                }
              ]
            },
            "method": "DELETE",
            "header": [
              {
                "key": "Content-Type",
                "value": "application/json",
                "type": "text"
              }
            ],
            "body": {
              "mode": "raw",
              "raw": "{\r\n  \"id\": 3\r\n}",
              "options": {
                "raw": {
                  "language": "json"
                }
              }
            },
            "url": {
              "raw": "{{base_url}}/cidade/delete",
              "host": [
                "{{base_url}}"
              ],
              "path": [
                "cidade",
                "delete"
              ]
            }
          },
          "response": []
        }
      ]
    },
    {
      "name": "Usuarios",
      "item": [
        {
          "name": "CreateUsuarios",
          "request": {
            "auth": {
              "type": "bearer",
              "bearer": [
                {
                  "key": "token",
                  "value": "{{token}}",
                  "type": "string"
                }
              ]
            },
            "method": "POST",
            "header": [
              {
                "key": "Content-Type",
                "value": "application/json",
                "type": "text"
              }
            ],
            "body": {
              "mode": "raw",
              "raw": "{\r\n  \"nome\": \"USER\",\r\n  \"email\": \"user@teste.com\",\r\n  \"senha\": \"Teste22@@\",\r\n  \"roleId\": 2\r\n}\r\n",
              "options": {
                "raw": {
                  "language": "json"
                }
              }
            },
            "url": {
              "raw": "{{base_url}}/usuario/create",
              "host": [
                "{{base_url}}"
              ],
              "path": [
                "usuario",
                "create"
              ]
            }
          },
          "response": []
        },
        {
          "name": "ListUsuarios",
          "protocolProfileBehavior": {
            "disableBodyPruning": true
          },
          "request": {
            "auth": {
              "type": "bearer",
              "bearer": [
                {
                  "key": "token",
                  "value": "{{token}}",
                  "type": "string"
                }
              ]
            },
            "method": "GET",
            "header": [
              {
                "key": "Content-Type",
                "value": "application/json",
                "type": "text"
              }
            ],
            "body": {
              "mode": "raw",
              "raw": "",
              "options": {
                "raw": {
                  "language": "json"
                }
              }
            },
            "url": {
              "raw": "{{base_url}}/usuario/list",
              "host": [
                "{{base_url}}"
              ],
              "path": [
                "usuario",
                "list"
              ]
            }
          },
          "response": []
        },
        {
          "name": "UpdateUsuarios",
          "request": {
            "auth": {
              "type": "bearer",
              "bearer": [
                {
                  "key": "token",
                  "value": "{{token}}",
                  "type": "string"
                }
              ]
            },
            "method": "PUT",
            "header": [
              {
                "key": "Content-Type",
                "value": "application/json",
                "type": "text"
              }
            ],
            "body": {
              "mode": "raw",
              "raw": "{\r\n  \"id\": 1,\r\n  \"nome\": \"Cayque Guilherme de Alvarenga Carmo\",\r\n  \"email\": \"cayque.142@gmail.com\",\r\n  \"roleId\": 1,\r\n  \"ativo\": true\r\n}",
              "options": {
                "raw": {
                  "language": "json"
                }
              }
            },
            "url": {
              "raw": "{{base_url}}/usuario/update",
              "host": [
                "{{base_url}}"
              ],
              "path": [
                "usuario",
                "update"
              ]
            }
          },
          "response": []
        },
        {
          "name": "DeleteUsuarios",
          "request": {
            "auth": {
              "type": "bearer",
              "bearer": [
                {
                  "key": "token",
                  "value": "{{token}}",
                  "type": "string"
                }
              ]
            },
            "method": "DELETE",
            "header": [
              {
                "key": "Content-Type",
                "value": "application/json",
                "type": "text"
              }
            ],
            "body": {
              "mode": "raw",
              "raw": "{\r\n  \"id\": 3\r\n}",
              "options": {
                "raw": {
                  "language": "json"
                }
              }
            },
            "url": {
              "raw": "{{base_url}}/usuario/delete",
              "host": [
                "{{base_url}}"
              ],
              "path": [
                "usuario",
                "delete"
              ]
            }
          },
          "response": []
        }
      ]
    },
    {
      "name": "RolesUsuarios",
      "item": [
        {
          "name": "CreateRole",
          "request": {
            "auth": {
              "type": "bearer",
              "bearer": [
                {
                  "key": "token",
                  "value": "{{token}}",
                  "type": "string"
                }
              ]
            },
            "method": "POST",
            "header": [
              {
                "key": "Content-Type",
                "value": "application/json",
                "type": "text"
              }
            ],
            "body": {
              "mode": "raw",
              "raw": "{\r\n  \"nomeRole\": \"Teste\"\r\n}",
              "options": {
                "raw": {
                  "language": "json"
                }
              }
            },
            "url": {
              "raw": "{{base_url}}/roleusuarios/create",
              "host": [
                "{{base_url}}"
              ],
              "path": [
                "roleusuarios",
                "create"
              ]
            }
          },
          "response": []
        },
        {
          "name": "ListRoles",
          "protocolProfileBehavior": {
            "disableBodyPruning": true
          },
          "request": {
            "auth": {
              "type": "bearer",
              "bearer": [
                {
                  "key": "token",
                  "value": "{{token}}",
                  "type": "string"
                }
              ]
            },
            "method": "GET",
            "header": [
              {
                "key": "Content-Type",
                "value": "application/json",
                "type": "text"
              }
            ],
            "body": {
              "mode": "raw",
              "raw": "",
              "options": {
                "raw": {
                  "language": "json"
                }
              }
            },
            "url": {
              "raw": "{{base_url}}/roleusuarios/list",
              "host": [
                "{{base_url}}"
              ],
              "path": [
                "roleusuarios",
                "list"
              ]
            }
          },
          "response": []
        },
        {
          "name": "UpdateRole",
          "request": {
            "auth": {
              "type": "bearer",
              "bearer": [
                {
                  "key": "token",
                  "value": "{{token}}",
                  "type": "string"
                }
              ]
            },
            "method": "PUT",
            "header": [
              {
                "key": "Content-Type",
                "value": "application/json",
                "type": "text"
              }
            ],
            "body": {
              "mode": "raw",
              "raw": "{\r\n  \"id\": 4,\r\n  \"nomeRole\": \"TesteUpdate\"\r\n}",
              "options": {
                "raw": {
                  "language": "json"
                }
              }
            },
            "url": {
              "raw": "{{base_url}}/roleusuarios/update",
              "host": [
                "{{base_url}}"
              ],
              "path": [
                "roleusuarios",
                "update"
              ]
            }
          },
          "response": []
        },
        {
          "name": "DeleteRole",
          "request": {
            "auth": {
              "type": "bearer",
              "bearer": [
                {
                  "key": "token",
                  "value": "{{token}}",
                  "type": "string"
                }
              ]
            },
            "method": "DELETE",
            "header": [
              {
                "key": "Content-Type",
                "value": "application/json",
                "type": "text"
              }
            ],
            "body": {
              "mode": "raw",
              "raw": "{\r\n  \"id\": 4\r\n}",
              "options": {
                "raw": {
                  "language": "json"
                }
              }
            },
            "url": {
              "raw": "{{base_url}}/roleusuarios/delete",
              "host": [
                "{{base_url}}"
              ],
              "path": [
                "roleusuarios",
                "delete"
              ]
            }
          },
          "response": []
        }
      ]
    },
    {
      "name": "Estado",
      "item": [
        {
          "name": "CreateEstado",
          "request": {
            "auth": {
              "type": "bearer",
              "bearer": [
                {
                  "key": "token",
                  "value": "{{token}}",
                  "type": "string"
                }
              ]
            },
            "method": "POST",
            "header": [
              {
                "key": "Content-Type",
                "value": "application/json",
                "type": "text"
              }
            ],
            "body": {
              "mode": "raw",
              "raw": "{\r\n  \"nomeEstado\": \"Rio de Janeiro\",\r\n  \"uf\":\"RJ\"\r\n}",
              "options": {
                "raw": {
                  "language": "json"
                }
              }
            },
            "url": {
              "raw": "{{base_url}}/estado/create",
              "host": [
                "{{base_url}}"
              ],
              "path": [
                "estado",
                "create"
              ]
            }
          },
          "response": []
        },
        {
          "name": "ListEstado",
          "protocolProfileBehavior": {
            "disableBodyPruning": true
          },
          "request": {
            "auth": {
              "type": "bearer",
              "bearer": [
                {
                  "key": "token",
                  "value": "{{token}}",
                  "type": "string"
                }
              ]
            },
            "method": "GET",
            "header": [
              {
                "key": "Content-Type",
                "value": "application/json",
                "type": "text"
              }
            ],
            "body": {
              "mode": "raw",
              "raw": "",
              "options": {
                "raw": {
                  "language": "json"
                }
              }
            },
            "url": {
              "raw": "{{base_url}}/estado/list",
              "host": [
                "{{base_url}}"
              ],
              "path": [
                "estado",
                "list"
              ]
            }
          },
          "response": []
        },
        {
          "name": "UpdateEstado",
          "request": {
            "auth": {
              "type": "bearer",
              "bearer": [
                {
                  "key": "token",
                  "value": "{{token}}",
                  "type": "string"
                }
              ]
            },
            "method": "PUT",
            "header": [
              {
                "key": "Content-Type",
                "value": "application/json",
                "type": "text"
              }
            ],
            "body": {
              "mode": "raw",
              "raw": "{\r\n  \"id\":3,\r\n  \"nomeEstado\": \"Rio de Jaaaneiro\",\r\n  \"uf\":\"RJ\"\r\n}",
              "options": {
                "raw": {
                  "language": "json"
                }
              }
            },
            "url": {
              "raw": "{{base_url}}/estado/update",
              "host": [
                "{{base_url}}"
              ],
              "path": [
                "estado",
                "update"
              ]
            }
          },
          "response": []
        },
        {
          "name": "DeleteEstado",
          "request": {
            "auth": {
              "type": "bearer",
              "bearer": [
                {
                  "key": "token",
                  "value": "{{token}}",
                  "type": "string"
                }
              ]
            },
            "method": "DELETE",
            "header": [
              {
                "key": "Content-Type",
                "value": "application/json",
                "type": "text"
              }
            ],
            "body": {
              "mode": "raw",
              "raw": "{\r\n  \"id\": 3\r\n}",
              "options": {
                "raw": {
                  "language": "json"
                }
              }
            },
            "url": {
              "raw": "{{base_url}}/estado/delete",
              "host": [
                "{{base_url}}"
              ],
              "path": [
                "estado",
                "delete"
              ]
            }
          },
          "response": []
        }
      ]
    },
    {
      "name": "SituacaoClientes",
      "item": [
        {
          "name": "Create",
          "request": {
            "auth": {
              "type": "bearer",
              "bearer": [
                {
                  "key": "token",
                  "value": "{{token}}",
                  "type": "string"
                }
              ]
            },
            "method": "POST",
            "header": [
              {
                "key": "Content-Type",
                "value": "application/json",
                "type": "text"
              }
            ],
            "body": {
              "mode": "raw",
              "raw": "{\r\n  \"descricaoSituacao\": \"Teste\"\r\n}",
              "options": {
                "raw": {
                  "language": "json"
                }
              }
            },
            "url": {
              "raw": "{{base_url}}/situacaoclientes/create",
              "host": [
                "{{base_url}}"
              ],
              "path": [
                "situacaoclientes",
                "create"
              ]
            }
          },
          "response": []
        },
        {
          "name": "List",
          "protocolProfileBehavior": {
            "disableBodyPruning": true
          },
          "request": {
            "auth": {
              "type": "bearer",
              "bearer": [
                {
                  "key": "token",
                  "value": "{{token}}",
                  "type": "string"
                }
              ]
            },
            "method": "GET",
            "header": [
              {
                "key": "Content-Type",
                "value": "application/json",
                "type": "text"
              }
            ],
            "body": {
              "mode": "raw",
              "raw": "",
              "options": {
                "raw": {
                  "language": "json"
                }
              }
            },
            "url": {
              "raw": "{{base_url}}/situacaoclientes/list",
              "host": [
                "{{base_url}}"
              ],
              "path": [
                "situacaoclientes",
                "list"
              ]
            }
          },
          "response": []
        },
        {
          "name": "Update",
          "request": {
            "auth": {
              "type": "bearer",
              "bearer": [
                {
                  "key": "token",
                  "value": "{{token}}",
                  "type": "string"
                }
              ]
            },
            "method": "PUT",
            "header": [
              {
                "key": "Content-Type",
                "value": "application/json",
                "type": "text"
              }
            ],
            "body": {
              "mode": "raw",
              "raw": "{\r\n  \"id\": 4,\r\n  \"descricaoSituacao\": \"TesteUpdate\"\r\n}",
              "options": {
                "raw": {
                  "language": "json"
                }
              }
            },
            "url": {
              "raw": "{{base_url}}/situacaoclientes/update",
              "host": [
                "{{base_url}}"
              ],
              "path": [
                "situacaoclientes",
                "update"
              ]
            }
          },
          "response": []
        },
        {
          "name": "Delete",
          "request": {
            "auth": {
              "type": "bearer",
              "bearer": [
                {
                  "key": "token",
                  "value": "{{token}}",
                  "type": "string"
                }
              ]
            },
            "method": "DELETE",
            "header": [
              {
                "key": "Content-Type",
                "value": "application/json",
                "type": "text"
              }
            ],
            "body": {
              "mode": "raw",
              "raw": "{\r\n  \"id\": 4\r\n}",
              "options": {
                "raw": {
                  "language": "json"
                }
              }
            },
            "url": {
              "raw": "{{base_url}}/situacaoclientes/delete",
              "host": [
                "{{base_url}}"
              ],
              "path": [
                "situacaoclientes",
                "delete"
              ]
            }
          },
          "response": []
        }
      ]
    },
    {
      "name": "SituacaoOs",
      "item": [
        {
          "name": "Create",
          "request": {
            "auth": {
              "type": "bearer",
              "bearer": [
                {
                  "key": "token",
                  "value": "{{token}}",
                  "type": "string"
                }
              ]
            },
            "method": "POST",
            "header": [
              {
                "key": "Content-Type",
                "value": "application/json",
                "type": "text"
              }
            ],
            "body": {
              "mode": "raw",
              "raw": "{\r\n  \"descricaoSituacaoOs\": \"Teste\"\r\n}",
              "options": {
                "raw": {
                  "language": "json"
                }
              }
            },
            "url": {
              "raw": "{{base_url}}/situacaoos/create",
              "host": [
                "{{base_url}}"
              ],
              "path": [
                "situacaoos",
                "create"
              ]
            }
          },
          "response": []
        },
        {
          "name": "List",
          "protocolProfileBehavior": {
            "disableBodyPruning": true
          },
          "request": {
            "auth": {
              "type": "bearer",
              "bearer": [
                {
                  "key": "token",
                  "value": "{{token}}",
                  "type": "string"
                }
              ]
            },
            "method": "GET",
            "header": [
              {
                "key": "Content-Type",
                "value": "application/json",
                "type": "text"
              }
            ],
            "body": {
              "mode": "raw",
              "raw": "",
              "options": {
                "raw": {
                  "language": "json"
                }
              }
            },
            "url": {
              "raw": "{{base_url}}/situacaoos/list",
              "host": [
                "{{base_url}}"
              ],
              "path": [
                "situacaoos",
                "list"
              ]
            }
          },
          "response": []
        },
        {
          "name": "Update",
          "request": {
            "auth": {
              "type": "bearer",
              "bearer": [
                {
                  "key": "token",
                  "value": "{{token}}",
                  "type": "string"
                }
              ]
            },
            "method": "PUT",
            "header": [
              {
                "key": "Content-Type",
                "value": "application/json",
                "type": "text"
              }
            ],
            "body": {
              "mode": "raw",
              "raw": "{\r\n  \"id\": 4,\r\n  \"descricaoSituacaoOs\": \"TesteUpdate\"\r\n}",
              "options": {
                "raw": {
                  "language": "json"
                }
              }
            },
            "url": {
              "raw": "{{base_url}}/situacaoos/update",
              "host": [
                "{{base_url}}"
              ],
              "path": [
                "situacaoos",
                "update"
              ]
            }
          },
          "response": []
        },
        {
          "name": "Delete",
          "request": {
            "auth": {
              "type": "bearer",
              "bearer": [
                {
                  "key": "token",
                  "value": "{{token}}",
                  "type": "string"
                }
              ]
            },
            "method": "DELETE",
            "header": [
              {
                "key": "Content-Type",
                "value": "application/json",
                "type": "text"
              }
            ],
            "body": {
              "mode": "raw",
              "raw": "{\r\n  \"id\": 4\r\n}",
              "options": {
                "raw": {
                  "language": "json"
                }
              }
            },
            "url": {
              "raw": "{{base_url}}/situacaoos/delete",
              "host": [
                "{{base_url}}"
              ],
              "path": [
                "situacaoos",
                "delete"
              ]
            }
          },
          "response": []
        }
      ]
    },
    {
      "name": "StatusProduto",
      "item": [
        {
          "name": "Create",
          "request": {
            "auth": {
              "type": "bearer",
              "bearer": [
                {
                  "key": "token",
                  "value": "{{token}}",
                  "type": "string"
                }
              ]
            },
            "method": "POST",
            "header": [
              {
                "key": "Content-Type",
                "value": "application/json",
                "type": "text"
              }
            ],
            "body": {
              "mode": "raw",
              "raw": "{\r\n  \"descricaoStatus\": \"Teste\"\r\n}",
              "options": {
                "raw": {
                  "language": "json"
                }
              }
            },
            "url": {
              "raw": "{{base_url}}/statusproduto/create",
              "host": [
                "{{base_url}}"
              ],
              "path": [
                "statusproduto",
                "create"
              ]
            }
          },
          "response": []
        },
        {
          "name": "List",
          "protocolProfileBehavior": {
            "disableBodyPruning": true
          },
          "request": {
            "auth": {
              "type": "bearer",
              "bearer": [
                {
                  "key": "token",
                  "value": "{{token}}",
                  "type": "string"
                }
              ]
            },
            "method": "GET",
            "header": [
              {
                "key": "Content-Type",
                "value": "application/json",
                "type": "text"
              }
            ],
            "body": {
              "mode": "raw",
              "raw": "",
              "options": {
                "raw": {
                  "language": "json"
                }
              }
            },
            "url": {
              "raw": "{{base_url}}/statusproduto/list",
              "host": [
                "{{base_url}}"
              ],
              "path": [
                "statusproduto",
                "list"
              ]
            }
          },
          "response": []
        },
        {
          "name": "Update",
          "request": {
            "auth": {
              "type": "bearer",
              "bearer": [
                {
                  "key": "token",
                  "value": "{{token}}",
                  "type": "string"
                }
              ]
            },
            "method": "PUT",
            "header": [
              {
                "key": "Content-Type",
                "value": "application/json",
                "type": "text"
              }
            ],
            "body": {
              "mode": "raw",
              "raw": "{\r\n  \"id\": 4,\r\n  \"descricaoStatus\": \"TesteUpdate\"\r\n}",
              "options": {
                "raw": {
                  "language": "json"
                }
              }
            },
            "url": {
              "raw": "{{base_url}}/statusproduto/update",
              "host": [
                "{{base_url}}"
              ],
              "path": [
                "statusproduto",
                "update"
              ]
            }
          },
          "response": []
        },
        {
          "name": "Delete",
          "request": {
            "auth": {
              "type": "bearer",
              "bearer": [
                {
                  "key": "token",
                  "value": "{{token}}",
                  "type": "string"
                }
              ]
            },
            "method": "DELETE",
            "header": [
              {
                "key": "Content-Type",
                "value": "application/json",
                "type": "text"
              }
            ],
            "body": {
              "mode": "raw",
              "raw": "{\r\n  \"id\": 4\r\n}",
              "options": {
                "raw": {
                  "language": "json"
                }
              }
            },
            "url": {
              "raw": "{{base_url}}/statusproduto/delete",
              "host": [
                "{{base_url}}"
              ],
              "path": [
                "statusproduto",
                "delete"
              ]
            }
          },
          "response": []
        }
      ]
    },
    {
      "name": "TipoPrazoGarantia",
      "item": [
        {
          "name": "Create",
          "request": {
            "auth": {
              "type": "bearer",
              "bearer": [
                {
                  "key": "token",
                  "value": "{{token}}",
                  "type": "string"
                }
              ]
            },
            "method": "POST",
            "header": [
              {
                "key": "Content-Type",
                "value": "application/json",
                "type": "text"
              }
            ],
            "body": {
              "mode": "raw",
              "raw": "{\r\n  \"descricaoPrazo\": \"BIM\"\r\n}",
              "options": {
                "raw": {
                  "language": "json"
                }
              }
            },
            "url": {
              "raw": "{{base_url}}/tipoprazogarantia/create",
              "host": [
                "{{base_url}}"
              ],
              "path": [
                "tipoprazogarantia",
                "create"
              ]
            }
          },
          "response": []
        },
        {
          "name": "List",
          "protocolProfileBehavior": {
            "disableBodyPruning": true
          },
          "request": {
            "auth": {
              "type": "bearer",
              "bearer": [
                {
                  "key": "token",
                  "value": "{{token}}",
                  "type": "string"
                }
              ]
            },
            "method": "GET",
            "header": [
              {
                "key": "Content-Type",
                "value": "application/json",
                "type": "text"
              }
            ],
            "body": {
              "mode": "raw",
              "raw": "",
              "options": {
                "raw": {
                  "language": "json"
                }
              }
            },
            "url": {
              "raw": "{{base_url}}/tipoprazogarantia/list",
              "host": [
                "{{base_url}}"
              ],
              "path": [
                "tipoprazogarantia",
                "list"
              ]
            }
          },
          "response": []
        },
        {
          "name": "Update",
          "request": {
            "auth": {
              "type": "bearer",
              "bearer": [
                {
                  "key": "token",
                  "value": "{{token}}",
                  "type": "string"
                }
              ]
            },
            "method": "PUT",
            "header": [
              {
                "key": "Content-Type",
                "value": "application/json",
                "type": "text"
              }
            ],
            "body": {
              "mode": "raw",
              "raw": "{\r\n  \"id\": 4,\r\n  \"descricaoPrazo\": \"SEM\"\r\n}",
              "options": {
                "raw": {
                  "language": "json"
                }
              }
            },
            "url": {
              "raw": "{{base_url}}/tipoprazogarantia/update",
              "host": [
                "{{base_url}}"
              ],
              "path": [
                "tipoprazogarantia",
                "update"
              ]
            }
          },
          "response": []
        },
        {
          "name": "Delete",
          "request": {
            "auth": {
              "type": "bearer",
              "bearer": [
                {
                  "key": "token",
                  "value": "{{token}}",
                  "type": "string"
                }
              ]
            },
            "method": "DELETE",
            "header": [
              {
                "key": "Content-Type",
                "value": "application/json",
                "type": "text"
              }
            ],
            "body": {
              "mode": "raw",
              "raw": "{\r\n  \"id\": 4\r\n}",
              "options": {
                "raw": {
                  "language": "json"
                }
              }
            },
            "url": {
              "raw": "{{base_url}}/tipoprazogarantia/delete",
              "host": [
                "{{base_url}}"
              ],
              "path": [
                "tipoprazogarantia",
                "delete"
              ]
            }
          },
          "response": []
        }
      ]
    },
    {
      "name": "Enderecos",
      "item": [
        {
          "name": "Create",
          "request": {
            "auth": {
              "type": "bearer",
              "bearer": [
                {
                  "key": "token",
                  "value": "{{token}}",
                  "type": "string"
                }
              ]
            },
            "method": "POST",
            "header": [
              {
                "key": "Content-Type",
                "value": "application/json",
                "type": "text"
              }
            ],
            "body": {
              "mode": "raw",
              "raw": "{\r\n  \"logradouro\": \"Rua Teste\",\r\n  \"bairro\": \"Bassan\",\r\n  \"cep\": \"11111-111\",\r\n  \"cidadeId\": 1,\r\n  \"complementoEndereco\": \"\"\r\n}",
              "options": {
                "raw": {
                  "language": "json"
                }
              }
            },
            "url": {
              "raw": "{{base_url}}/endereco/create",
              "host": [
                "{{base_url}}"
              ],
              "path": [
                "endereco",
                "create"
              ]
            }
          },
          "response": []
        },
        {
          "name": "List",
          "protocolProfileBehavior": {
            "disableBodyPruning": true
          },
          "request": {
            "auth": {
              "type": "bearer",
              "bearer": [
                {
                  "key": "token",
                  "value": "{{token}}",
                  "type": "string"
                }
              ]
            },
            "method": "GET",
            "header": [
              {
                "key": "Content-Type",
                "value": "application/json",
                "type": "text"
              }
            ],
            "body": {
              "mode": "raw",
              "raw": "",
              "options": {
                "raw": {
                  "language": "json"
                }
              }
            },
            "url": {
              "raw": "{{base_url}}/endereco/list",
              "host": [
                "{{base_url}}"
              ],
              "path": [
                "endereco",
                "list"
              ]
            }
          },
          "response": []
        },
        {
          "name": "Update",
          "request": {
            "auth": {
              "type": "bearer",
              "bearer": [
                {
                  "key": "token",
                  "value": "{{token}}",
                  "type": "string"
                }
              ]
            },
            "method": "PUT",
            "header": [
              {
                "key": "Content-Type",
                "value": "application/json",
                "type": "text"
              }
            ],
            "body": {
              "mode": "raw",
              "raw": "{\r\n  \"id\": 2,\r\n  \"logradouro\": \"Rua Teste Update\",\r\n  \"bairro\": \"Update\",\r\n  \"cep\": \"22222-222\",\r\n  \"cidadeId\": 1,\r\n  \"complementoEndereco\": \"\"\r\n}",
              "options": {
                "raw": {
                  "language": "json"
                }
              }
            },
            "url": {
              "raw": "{{base_url}}/endereco/update",
              "host": [
                "{{base_url}}"
              ],
              "path": [
                "endereco",
                "update"
              ]
            }
          },
          "response": []
        },
        {
          "name": "Delete",
          "request": {
            "auth": {
              "type": "bearer",
              "bearer": [
                {
                  "key": "token",
                  "value": "{{token}}",
                  "type": "string"
                }
              ]
            },
            "method": "DELETE",
            "header": [
              {
                "key": "Content-Type",
                "value": "application/json",
                "type": "text"
              }
            ],
            "body": {
              "mode": "raw",
              "raw": "{\r\n  \"id\": 2\r\n}",
              "options": {
                "raw": {
                  "language": "json"
                }
              }
            },
            "url": {
              "raw": "{{base_url}}/endereco/delete",
              "host": [
                "{{base_url}}"
              ],
              "path": [
                "endereco",
                "delete"
              ]
            }
          },
          "response": []
        }
      ]
    },
    {
      "name": "Clientes",
      "item": [
        {
          "name": "Create",
          "request": {
            "auth": {
              "type": "bearer",
              "bearer": [
                {
                  "key": "token",
                  "value": "{{token}}",
                  "type": "string"
                }
              ]
            },
            "method": "POST",
            "header": [
              {
                "key": "Content-Type",
                "value": "application/json",
                "type": "text"
              }
            ],
            "body": {
              "mode": "raw",
              "raw": "{\r\n  \"nomeCliente\": \"Cliente Teste\",\r\n  \"cpf\": \"111.111.111-11\",\r\n  \"situacaoClienteId\": 1,\r\n  \"enderecoId\": 1,\r\n  \"numeroEndereco\": \"222\",\r\n  \"complementoCliente\":\"Casa\"\r\n}",
              "options": {
                "raw": {
                  "language": "json"
                }
              }
            },
            "url": {
              "raw": "{{base_url}}/cliente/create",
              "host": [
                "{{base_url}}"
              ],
              "path": [
                "cliente",
                "create"
              ]
            }
          },
          "response": []
        },
        {
          "name": "List",
          "protocolProfileBehavior": {
            "disableBodyPruning": true
          },
          "request": {
            "auth": {
              "type": "bearer",
              "bearer": [
                {
                  "key": "token",
                  "value": "{{token}}",
                  "type": "string"
                }
              ]
            },
            "method": "GET",
            "header": [
              {
                "key": "Content-Type",
                "value": "application/json",
                "type": "text"
              }
            ],
            "body": {
              "mode": "raw",
              "raw": "",
              "options": {
                "raw": {
                  "language": "json"
                }
              }
            },
            "url": {
              "raw": "{{base_url}}/cliente/list",
              "host": [
                "{{base_url}}"
              ],
              "path": [
                "cliente",
                "list"
              ]
            }
          },
          "response": []
        },
        {
          "name": "Update",
          "request": {
            "auth": {
              "type": "bearer",
              "bearer": [
                {
                  "key": "token",
                  "value": "{{token}}",
                  "type": "string"
                }
              ]
            },
            "method": "PUT",
            "header": [
              {
                "key": "Content-Type",
                "value": "application/json",
                "type": "text"
              }
            ],
            "body": {
              "mode": "raw",
              "raw": "{\r\n  \"id\": 2,\r\n  \"nomeCliente\": \"Cliente Teste Update\",\r\n  \"cpf\": \"111.111.111-22\",\r\n  \"situacaoClienteId\": 3,\r\n  \"enderecoId\": 1,\r\n  \"numeroEndereco\": \"123\",\r\n  \"complementoCliente\":\"Casa\"\r\n}",
              "options": {
                "raw": {
                  "language": "json"
                }
              }
            },
            "url": {
              "raw": "{{base_url}}/cliente/update",
              "host": [
                "{{base_url}}"
              ],
              "path": [
                "cliente",
                "update"
              ]
            }
          },
          "response": []
        },
        {
          "name": "Delete",
          "request": {
            "auth": {
              "type": "bearer",
              "bearer": [
                {
                  "key": "token",
                  "value": "{{token}}",
                  "type": "string"
                }
              ]
            },
            "method": "DELETE",
            "header": [
              {
                "key": "Content-Type",
                "value": "application/json",
                "type": "text"
              }
            ],
            "body": {
              "mode": "raw",
              "raw": "{\r\n  \"id\": 2\r\n}",
              "options": {
                "raw": {
                  "language": "json"
                }
              }
            },
            "url": {
              "raw": "{{base_url}}/cliente/delete",
              "host": [
                "{{base_url}}"
              ],
              "path": [
                "cliente",
                "delete"
              ]
            }
          },
          "response": []
        }
      ]
    },
    {
      "name": "Produtos",
      "item": [
        {
          "name": "Create",
          "request": {
            "auth": {
              "type": "bearer",
              "bearer": [
                {
                  "key": "token",
                  "value": "{{token}}",
                  "type": "string"
                }
              ]
            },
            "method": "POST",
            "header": [
              {
                "key": "Content-Type",
                "value": "application/json",
                "type": "text"
              }
            ],
            "body": {
              "mode": "raw",
              "raw": "{\r\n  \"codProduto\": 1122,\r\n  \"descricaoProduto\": \"Prod Teste\",\r\n  \"valorProduto\": 1,\r\n  \"statusId\": 1,\r\n  \"tipoPrazoGarantiaId\": 2,\r\n  \"tempoGarantia\": 3\r\n}",
              "options": {
                "raw": {
                  "language": "json"
                }
              }
            },
            "url": {
              "raw": "{{base_url}}/produto/create",
              "host": [
                "{{base_url}}"
              ],
              "path": [
                "produto",
                "create"
              ]
            }
          },
          "response": []
        },
        {
          "name": "List",
          "protocolProfileBehavior": {
            "disableBodyPruning": true
          },
          "request": {
            "auth": {
              "type": "bearer",
              "bearer": [
                {
                  "key": "token",
                  "value": "{{token}}",
                  "type": "string"
                }
              ]
            },
            "method": "GET",
            "header": [
              {
                "key": "Content-Type",
                "value": "application/json",
                "type": "text"
              }
            ],
            "body": {
              "mode": "raw",
              "raw": "",
              "options": {
                "raw": {
                  "language": "json"
                }
              }
            },
            "url": {
              "raw": "{{base_url}}/produto/list",
              "host": [
                "{{base_url}}"
              ],
              "path": [
                "produto",
                "list"
              ]
            }
          },
          "response": []
        },
        {
          "name": "Update",
          "request": {
            "auth": {
              "type": "bearer",
              "bearer": [
                {
                  "key": "token",
                  "value": "{{token}}",
                  "type": "string"
                }
              ]
            },
            "method": "PUT",
            "header": [
              {
                "key": "Content-Type",
                "value": "application/json",
                "type": "text"
              }
            ],
            "body": {
              "mode": "raw",
              "raw": "{\r\n  \"id\": 2,\r\n  \"codProduto\": 1234,\r\n  \"descricaoProduto\": \"Prod Teste Update\",\r\n  \"valorProduto\": 10.00,\r\n  \"statusId\": 3,\r\n  \"tipoPrazoGarantiaId\": 2,\r\n  \"tempoGarantia\": 0\r\n}",
              "options": {
                "raw": {
                  "language": "json"
                }
              }
            },
            "url": {
              "raw": "{{base_url}}/produto/update",
              "host": [
                "{{base_url}}"
              ],
              "path": [
                "produto",
                "update"
              ]
            }
          },
          "response": []
        },
        {
          "name": "Delete",
          "request": {
            "auth": {
              "type": "bearer",
              "bearer": [
                {
                  "key": "token",
                  "value": "{{token}}",
                  "type": "string"
                }
              ]
            },
            "method": "DELETE",
            "header": [
              {
                "key": "Content-Type",
                "value": "application/json",
                "type": "text"
              }
            ],
            "body": {
              "mode": "raw",
              "raw": "{\r\n  \"id\": 2\r\n}",
              "options": {
                "raw": {
                  "language": "json"
                }
              }
            },
            "url": {
              "raw": "{{base_url}}/produto/delete",
              "host": [
                "{{base_url}}"
              ],
              "path": [
                "produto",
                "delete"
              ]
            }
          },
          "response": []
        }
      ]
    },
    {
      "name": "OrdensServico",
      "item": [
        {
          "name": "Create",
          "request": {
            "auth": {
              "type": "bearer",
              "bearer": [
                {
                  "key": "token",
                  "value": "{{token}}",
                  "type": "string"
                }
              ]
            },
            "method": "POST",
            "header": [
              {
                "key": "Content-Type",
                "value": "application/json",
                "type": "text"
              }
            ],
            "body": {
              "mode": "raw",
              "raw": "{\r\n  \"numOs\": 1001,\r\n  \"situacaoOsId\": 1,\r\n  \"produtoId\": 1,\r\n  \"cidadeId\": 1,\r\n  \"observacao\": \"Cliente relatou problema no equipamento\",\r\n  \"cliente\": {\r\n    \"nomeCliente\": \"João da Silva\",\r\n    \"cpf\": \"12345678900\",\r\n    \"situacaoClienteId\": 1,\r\n    \"enderecoId\": 1,\r\n    \"numeroEndereco\": 120,\r\n    \"complementoCliente\": \"Casa A\"\r\n  }\r\n}",
              "options": {
                "raw": {
                  "language": "json"
                }
              }
            },
            "url": {
              "raw": "{{base_url}}/ordemservico/create",
              "host": [
                "{{base_url}}"
              ],
              "path": [
                "ordemservico",
                "create"
              ]
            }
          },
          "response": []
        },
        {
          "name": "List",
          "protocolProfileBehavior": {
            "disableBodyPruning": true
          },
          "request": {
            "auth": {
              "type": "bearer",
              "bearer": [
                {
                  "key": "token",
                  "value": "{{token}}",
                  "type": "string"
                }
              ]
            },
            "method": "GET",
            "header": [
              {
                "key": "Content-Type",
                "value": "application/json",
                "type": "text"
              }
            ],
            "body": {
              "mode": "raw",
              "raw": "",
              "options": {
                "raw": {
                  "language": "json"
                }
              }
            },
            "url": {
              "raw": "{{base_url}}/ordemservico/list",
              "host": [
                "{{base_url}}"
              ],
              "path": [
                "ordemservico",
                "list"
              ]
            }
          },
          "response": []
        },
        {
          "name": "Update",
          "request": {
            "auth": {
              "type": "bearer",
              "bearer": [
                {
                  "key": "token",
                  "value": "{{token}}",
                  "type": "string"
                }
              ]
            },
            "method": "PUT",
            "header": [
              {
                "key": "Content-Type",
                "value": "application/json",
                "type": "text"
              }
            ],
            "body": {
              "mode": "raw",
              "raw": "{\r\n  \"id\": 1,\r\n  \"numOs\": 1001,\r\n  \"situacaoOsId\": 2,\r\n  \"clienteId\": 1,\r\n  \"produtoId\": 2,\r\n  \"cidadeId\": 1,\r\n  \"observacao\": \"Equipamento em atendimento\"\r\n}",
              "options": {
                "raw": {
                  "language": "json"
                }
              }
            },
            "url": {
              "raw": "{{base_url}}/ordemservico/update",
              "host": [
                "{{base_url}}"
              ],
              "path": [
                "ordemservico",
                "update"
              ]
            }
          },
          "response": []
        },
        {
          "name": "Delete",
          "request": {
            "auth": {
              "type": "bearer",
              "bearer": [
                {
                  "key": "token",
                  "value": "{{token}}",
                  "type": "string"
                }
              ]
            },
            "method": "DELETE",
            "header": [
              {
                "key": "Content-Type",
                "value": "application/json",
                "type": "text"
              }
            ],
            "body": {
              "mode": "raw",
              "raw": "{\r\n  \"id\": 2\r\n}",
              "options": {
                "raw": {
                  "language": "json"
                }
              }
            },
            "url": {
              "raw": "{{base_url}}/produto/delete",
              "host": [
                "{{base_url}}"
              ],
              "path": [
                "produto",
                "delete"
              ]
            }
          },
          "response": []
        }
      ]
    },
    {
      "name": "OrdensServicoLogs",
      "item": [
        {
          "name": "List",
          "protocolProfileBehavior": {
            "disableBodyPruning": true
          },
          "request": {
            "auth": {
              "type": "bearer",
              "bearer": [
                {
                  "key": "token",
                  "value": "{{token}}",
                  "type": "string"
                }
              ]
            },
            "method": "GET",
            "header": [
              {
                "key": "Content-Type",
                "value": "application/json",
                "type": "text"
              }
            ],
            "body": {
              "mode": "raw",
              "raw": "{\r\n    \"ordemServicoId\": 2\r\n}",
              "options": {
                "raw": {
                  "language": "json"
                }
              }
            },
            "url": {
              "raw": "{{base_url}}/ordemservicologs/listByOrdemServico?ordemServicoId=2",
              "host": [
                "{{base_url}}"
              ],
              "path": [
                "ordemservicologs",
                "listByOrdemServico"
              ],
              "query": [
                {
                  "key": "ordemServicoId",
                  "value": "2"
                }
              ]
            }
          },
          "response": []
        }
      ]
    },
    {
      "name": "Auth",
      "item": [
        {
          "name": "Login",
          "event": [
            {
              "listen": "test",
              "script": {
                "exec": [
                  "const response = pm.response.json();",
                  "",
                  "if (response && response.data && response.data.token) {",
                  "    pm.collectionVariables.set('token', response.data.token);",
                  "}"
                ],
                "type": "text/javascript",
                "packages": {},
                "requests": {}
              }
            }
          ],
          "request": {
            "method": "POST",
            "header": [
              {
                "key": "Content-Type",
                "value": "application/json",
                "type": "text"
              }
            ],
            "body": {
              "mode": "raw",
              "raw": "{\r\n  \"email\": \"admin@teste.com\",\r\n  \"senha\": \"Teste11@@\"\r\n}",
              "options": {
                "raw": {
                  "language": "json"
                }
              }
            },
            "url": {
              "raw": "{{base_url}}/auth/login",
              "host": [
                "{{base_url}}"
              ],
              "path": [
                "auth",
                "login"
              ]
            }
          },
          "response": []
        }
      ]
    }
  ],
  "auth": {
    "type": "bearer"
  },
  "variable": [
    {
      "key": "base_url",
      "value": "http://localhost:8000"
    },
    {
      "key": "token",
      "value": ""
    }
  ]
}